aiscot/VERSION
aiscot/__init__.py
aiscot/ais_functions.py
aiscot/classes.py
aiscot/commands.py
aiscot/constants.py
aiscot/functions.py
aiscot/pyAISm.py
aiscot/data/MaritimeIdentificationDigits-bb62983a-cf0e-40a1-9431-cd54eaeb1c85.csv
aiscot/data/yadd_mmsi_coast_2021-11-03-163012.txt
aiscot/data/yadd_mmsi_ship_2023-02-11-001541.txt
aiscot-7.1.3.dist-info/licenses/LICENSE
aiscot-7.1.3.dist-info/METADATA
aiscot-7.1.3.dist-info/WHEEL
aiscot-7.1.3.dist-info/entry_points.txt
aiscot-7.1.3.dist-info/top_level.txt
aiscot-7.1.3.dist-info/RECORD
