Metadata-Version: 2.4
Name: aiscot
Version: 7.1.3
Summary: Software for monitoring and analyzing AIS in TAK.
Home-page: https://github.com/snstac/aiscot
Maintainer: Greg Albrecht <oss@undef.net>
Maintainer-email: oss@undef.net
License: Apache 2.0
Project-URL: CI: GitHub Actions, https://github.com/snstac/aiscot/actions
Project-URL: GitHub: issues, https://github.com/snstac/aiscot/issues
Project-URL: GitHub: repo, https://github.com/snstac/aiscot
Keywords: Cursor on Target,Cursor-on-Target,CoT,ATAK,TAK,WinTAK,TAK,TAK Server,iTAK,AIS,Boats,Marine,Sailing,Ships,Shipping
Classifier: License :: OSI Approved :: Apache Software License
Classifier: Intended Audience :: Developers
Classifier: Programming Language :: Python
Classifier: Programming Language :: Python :: 3
Classifier: Programming Language :: Python :: 3 :: Only
Classifier: Development Status :: 5 - Production/Stable
Classifier: Operating System :: POSIX
Classifier: Operating System :: MacOS :: MacOS X
Classifier: Operating System :: Microsoft :: Windows
Classifier: Operating System :: OS Independent
Requires-Python: <4,>=3.6
License-File: LICENSE
Requires-Dist: pytak>=5.4.0
Requires-Dist: aiohttp<4.0.0
Requires-Dist: importlib_resources; python_version < "3.9"
Provides-Extra: with-takproto
Requires-Dist: takproto>=2.0.0; extra == "with-takproto"
Provides-Extra: test
Requires-Dist: pytest-asyncio; extra == "test"
Requires-Dist: pytest-cov; extra == "test"
Requires-Dist: pylint; extra == "test"
Requires-Dist: flake8; extra == "test"
Requires-Dist: black; extra == "test"
Requires-Dist: pytak; extra == "test"
Dynamic: license-file
